[
  {
    "id": "1778346688271",
    "userId": "1778345621758",
    "name": "dff",
    "filters": {
      "months": [],
      "ownerships": [
        "上海母公司",
        "常州酒店",
        "宜兴（华东分）",
        "南京酒店",
        "黄山酒店",
        "无锡酒店",
        "合并抵消",
        "华东分抵消"
      ],
      "managements": [
        "上海酒店项目部"
      ],
      "propertyTypes": [
        "物业业务",
        "餐饮业务",
        "其他业务",
        "酒店业务",
        "租赁业务",
        "管理业务"
      ],
      "projectNames": [
        "222200150308-中石化海洋局商城路基地物业服务项目",
        "222200150307-中石化海洋局商城路基地配餐项目",
        "222200150304-上海酒店能源转售项目",
        "222200150303-上海酒店",
        "222200150309-国家管网集团上海区域总部后勤配餐项目",
        "222200150241-中石油上海临港新材料研究院物业项目",
        "222200150239-蓝海新材料江苏物业项目",
        "222200150238-蓝海新材料江苏配餐项目",
        "222200150310-国家管网集团上海区域总部后勤物业服务项目",
        "222200150504-江苏销售分公司配餐业务",
        "222200150502-江苏常州酒店能源转售",
        "222200150501-常州酒店",
        "222200150236-江苏太仓燃气公司配餐项目-代理",
        "222200150214-上海酒店租赁项目",
        "222200150215-上海同盛大厦项目",
        "222200150505-江苏泰州销售配餐项目",
        "222200150231-世纪大道中石油上海大厦能源转售项目",
        "222200150230-上海世纪大道中石油综合餐饮项目",
        "222200150229-上海世纪大道中石油综合物业项目",
        "222200150228-川沙影院保洁项目",
        "222200150227-长泰影院保洁项目",
        "222200150225-寰球工程保洁项目",
        "222200150224-寰球工程安保项目",
        "222200150223-华东化工仓储安保项目",
        "222200150222-豪孚迪安保项目",
        "222200150217-华东分公司本部",
        "2222001501-宜兴度假村项目租赁项目（华东分）",
        "222200150506-江苏南通销售分公司配餐业务",
        "222200150508-浙江销售分公司配餐业务",
        "222200150915-蓝海新材料江苏配餐项目-代理",
        "222200150801-黄山阳光酒店分公司",
        "222200150914-天然气安徽分配餐项目",
        "222200150608-无锡销售配餐项目",
        "222200150607-天然气连云港销售分公司配餐项目",
        "222200150606-无锡润滑脂配餐项目",
        "222200150913-合肥昆仑燃气配餐项目",
        "222200150912-江苏苏州销售分公司江乾站配餐项目",
        "222200150808-黄山项目部销售项目",
        "222200150901-秣陵路99号综合楼酒店整租项目",
        "222200150902-黄鹂新村8栋酒店整租项目",
        "222200150903-黄鹂新村、金斯利、南湖住宅其他资产租赁项目",
        "222200150906-南京酒店能源转售项目",
        "222200150908-中国移动南京分公司基站",
        "222200150909-中国铁塔南京市分公司基站",
        "222200150603-无锡酒店商品销售项目",
        "222200150602-荣巷门面房租赁项目",
        "222200150601-马山檀溪1号温特莱酒店租赁项目",
        "222200150523-中油锡山石油有限公司配餐项目",
        "222200150522-江苏盐城销售分公司劳务输出",
        "222200150521-江苏苏州销售分公司劳务输出",
        "222200150520-江苏南京销售分公司劳务输出",
        "222200150519-江苏非油销售公司劳务输出",
        "222200150510-浙江湖州销售分公司配餐业务",
        "222200150507-江苏中石油国际事业有限公司配餐业务",
        "222200150527-东北销售浙江宁波分公司配餐业务",
        "222200150542-浙江湖州销售分公司配餐业务",
        "222200150541-浙江金华销售分公司配餐劳务输出项目",
        "222200150540-浙江绍兴销售分公司配餐劳务输出项目",
        "222200150539-江苏太仓燃气公司配餐项目",
        "222200150538-浙江杭州地质研究院配餐项目",
        "222200150535-中石化天然气分公司浙江销售配餐项目",
        "222200150534-浙江杭州地质研究院办公物业项目",
        "222200150533-江苏常州销售分公司配餐项目",
        "222200150532-江苏镇江销售分公司劳务输出",
        "222200150531-江苏南京中石油联安石化办公物业",
        "222200150530-东北销售浙江宁波分公司办公物业",
        "222200150528-东北销售浙江南京分公司配餐业务",
        "222200150526-浙江杭州销售分公司劳务输出",
        "222200150904-南京项目部项目销售",
        "222200150233-合肥昆仑燃气配餐项目-代理",
        "222200150234-天然气安徽分配餐项目-代理",
        "222200150237-无锡润滑脂配餐项目-代理",
        "222200150240-中石油上海临港新材料研究院配餐项目",
        "222200150242-陆家嘴金融城白领文化艺术中心物业项目",
        "222200150605-荣巷门面房能源转售项目",
        "222200150209-浙江销售分公司配餐项目-代理",
        "222200150235-浙江杭州地质研究院配餐项目-代理",
        "222200150232-浙江杭州地质研究院办公物业项目-代理",
        "222200150916-中石油昆仑合燃压缩气配餐项目",
        "222200150202-浙江昆仑好客分公司配餐项目-代理",
        "222200150918-东北销售南京分计量服务项目",
        "222200150917-东北销售宁波分计量项目",
        "222200150244-昆仑工程辽阳江苏物业项目",
        "222200150213-上海酒店租赁项目",
        "222200150609-江苏泰州销售配餐项目",
        "SH3J25Z016-江苏淮安销售分公司配餐劳务项目",
        "SH3B25Z075-中油锡山石油有限公司配餐项目",
        "222200150243-华东化工销售江苏物业项目",
        "SH3525Z043-大连石化江苏配餐项目",
        "SH3B25Z078-苏州销售太仓实训基地",
        "SH3B25Z077-江苏苏州销售分公司劳务输出",
        "SH3J25Z017-江苏南京销售分公司劳务输出",
        "SH3B25Z076-浙江杭州销售分公司劳务输出",
        "SH3B25Z079-江苏苏州销售分公司江乾站配餐项目",
        "222200150524-  江苏华东燃气运输分公司劳务输出0092（已停用）",
        "222200150516-  浙江杭州临安昆仑燃气配餐业务0031（已停用）",
        "222200150511-  浙江嘉兴销售分公司配餐业务0031（已停用）",
        "222200150512-浙江金华销售分公司配餐劳务输出项目",
        "222200150509-  浙江昆仑好客分公司配餐业务0031",
        "222200150518-浙江绍兴销售分公司其他餐饮业务",
        "222200150536-常州酒店",
        "222200150537-常州酒店",
        "222200150525-江苏无锡销售分公司劳务输出",
        "SH3625Z027-常州酒店项目部销售费用",
        "222200150218-南京商品代销项目",
        "222200150203-天然气销售浙江分公司配餐项目-代理",
        "222200150201-浙江湖州销售分公司配餐项目-代理",
        "222200150205-浙江绍兴销售分公司配餐项目-代理",
        "SHDX001-上海抵消",
        "HDDX003-华东分抵消",
        "HDDX001-华东分抵消",
        "HDDX004-华东分抵消",
        "HDDX005-华东分抵消",
        "HDDX002-华东分抵消",
        "SH3B26Z001-浙江湖州销售分公司配餐业务",
        "SH3B26Z004-浙江金华销售分公司配餐劳务输出项目",
        "222200150810-浙江绍兴销售分公司配餐劳务项目-黄山",
        "SH3B26Z002-中石化天然气分公司浙江销售配餐项目",
        "222200150809-黄山项目部能源转售项目",
        "222200150905-中国石油运输有限公司江苏分公司配餐项目",
        "SH3J26Z001-江苏镇江销售分公司劳务输出",
        "222200150910-南京酒店项目部公摊部门",
        "222200150911-黄鹂新村朝天宫会议室场地租赁项目",
        "LHCXL-蓝海新材料新市场拓展+提质增效",
        "222200150311-上海酒店物业费",
        "222200150301-  海洋石油局PA保洁项目0011",
        "222200150305-上海酒店租赁项目-未启用",
        "222200150216-上海中石油大厦项目",
        "222200150219-石油大厦资产项目",
        "222200150226-  常信拍卖保洁项目0013",
        "222200150211-中国移动上海分公司保洁项目",
        "222200150212-  江西安徽宁波车辆租赁项目0089",
        "SH3B26Z005-东北销售浙江宁波分公司配餐业务",
        "SH3B26Z006-东北销售浙江宁波分公司办公物业",
        "SH3526Z005-昆冈制造江苏配餐项目",
        "SH3526Z004-昆仑物流江苏配餐项目",
        "SH3526Z006-兰州石化江苏配餐项目（新）",
        "SH3526Z001-蓝海生产管理楼江苏配餐项目",
        "SH3526Z003-中油电能江苏配餐项目",
        "SH3526Z002-中油国际事业江苏物业项目",
        "XZCY0012-新市场拓展",
        "XZZY0012-自有产品销售"
      ]
    },
    "timestamp": "2026-05-09T17:18:34.359Z",
    "selectedIndicators": [
      "收入YTD",
      "利润YTD",
      "15用工薪酬成本",
      "16外包劳务支出"
    ]
  },
  {
    "id": "1778346707795",
    "userId": "1778345621758",
    "name": "dfdfd",
    "filters": {
      "months": [],
      "ownerships": [
        "上海母公司",
        "常州酒店",
        "宜兴（华东分）",
        "南京酒店",
        "黄山酒店",
        "无锡酒店",
        "合并抵消",
        "华东分抵消"
      ],
      "managements": [
        "上海酒店项目部",
        "上海物业项目部",
        "南通蓝海项目部"
      ],
      "propertyTypes": [
        "物业业务",
        "餐饮业务",
        "其他业务",
        "酒店业务",
        "租赁业务",
        "管理业务"
      ],
      "projectNames": [
        "222200150308-中石化海洋局商城路基地物业服务项目",
        "222200150307-中石化海洋局商城路基地配餐项目",
        "222200150304-上海酒店能源转售项目",
        "222200150303-上海酒店",
        "222200150309-国家管网集团上海区域总部后勤配餐项目",
        "222200150241-中石油上海临港新材料研究院物业项目",
        "222200150239-蓝海新材料江苏物业项目",
        "222200150238-蓝海新材料江苏配餐项目",
        "222200150310-国家管网集团上海区域总部后勤物业服务项目",
        "222200150504-江苏销售分公司配餐业务",
        "222200150502-江苏常州酒店能源转售",
        "222200150501-常州酒店",
        "222200150236-江苏太仓燃气公司配餐项目-代理",
        "222200150214-上海酒店租赁项目",
        "222200150215-上海同盛大厦项目",
        "222200150505-江苏泰州销售配餐项目",
        "222200150231-世纪大道中石油上海大厦能源转售项目",
        "222200150230-上海世纪大道中石油综合餐饮项目",
        "222200150229-上海世纪大道中石油综合物业项目",
        "222200150228-川沙影院保洁项目",
        "222200150227-长泰影院保洁项目",
        "222200150225-寰球工程保洁项目",
        "222200150224-寰球工程安保项目",
        "222200150223-华东化工仓储安保项目",
        "222200150222-豪孚迪安保项目",
        "222200150217-华东分公司本部",
        "2222001501-宜兴度假村项目租赁项目（华东分）",
        "222200150506-江苏南通销售分公司配餐业务",
        "222200150508-浙江销售分公司配餐业务",
        "222200150915-蓝海新材料江苏配餐项目-代理",
        "222200150801-黄山阳光酒店分公司",
        "222200150914-天然气安徽分配餐项目",
        "222200150608-无锡销售配餐项目",
        "222200150607-天然气连云港销售分公司配餐项目",
        "222200150606-无锡润滑脂配餐项目",
        "222200150913-合肥昆仑燃气配餐项目",
        "222200150912-江苏苏州销售分公司江乾站配餐项目",
        "222200150808-黄山项目部销售项目",
        "222200150901-秣陵路99号综合楼酒店整租项目",
        "222200150902-黄鹂新村8栋酒店整租项目",
        "222200150903-黄鹂新村、金斯利、南湖住宅其他资产租赁项目",
        "222200150906-南京酒店能源转售项目",
        "222200150908-中国移动南京分公司基站",
        "222200150909-中国铁塔南京市分公司基站",
        "222200150603-无锡酒店商品销售项目",
        "222200150602-荣巷门面房租赁项目",
        "222200150601-马山檀溪1号温特莱酒店租赁项目",
        "222200150523-中油锡山石油有限公司配餐项目",
        "222200150522-江苏盐城销售分公司劳务输出",
        "222200150521-江苏苏州销售分公司劳务输出",
        "222200150520-江苏南京销售分公司劳务输出",
        "222200150519-江苏非油销售公司劳务输出",
        "222200150510-浙江湖州销售分公司配餐业务",
        "222200150507-江苏中石油国际事业有限公司配餐业务",
        "222200150527-东北销售浙江宁波分公司配餐业务",
        "222200150542-浙江湖州销售分公司配餐业务",
        "222200150541-浙江金华销售分公司配餐劳务输出项目",
        "222200150540-浙江绍兴销售分公司配餐劳务输出项目",
        "222200150539-江苏太仓燃气公司配餐项目",
        "222200150538-浙江杭州地质研究院配餐项目",
        "222200150535-中石化天然气分公司浙江销售配餐项目",
        "222200150534-浙江杭州地质研究院办公物业项目",
        "222200150533-江苏常州销售分公司配餐项目",
        "222200150532-江苏镇江销售分公司劳务输出",
        "222200150531-江苏南京中石油联安石化办公物业",
        "222200150530-东北销售浙江宁波分公司办公物业",
        "222200150528-东北销售浙江南京分公司配餐业务",
        "222200150526-浙江杭州销售分公司劳务输出",
        "222200150904-南京项目部项目销售",
        "222200150233-合肥昆仑燃气配餐项目-代理",
        "222200150234-天然气安徽分配餐项目-代理",
        "222200150237-无锡润滑脂配餐项目-代理",
        "222200150240-中石油上海临港新材料研究院配餐项目",
        "222200150242-陆家嘴金融城白领文化艺术中心物业项目",
        "222200150605-荣巷门面房能源转售项目",
        "222200150209-浙江销售分公司配餐项目-代理",
        "222200150235-浙江杭州地质研究院配餐项目-代理",
        "222200150232-浙江杭州地质研究院办公物业项目-代理",
        "222200150916-中石油昆仑合燃压缩气配餐项目",
        "222200150202-浙江昆仑好客分公司配餐项目-代理",
        "222200150918-东北销售南京分计量服务项目",
        "222200150917-东北销售宁波分计量项目",
        "222200150244-昆仑工程辽阳江苏物业项目",
        "222200150213-上海酒店租赁项目",
        "222200150609-江苏泰州销售配餐项目",
        "SH3J25Z016-江苏淮安销售分公司配餐劳务项目",
        "SH3B25Z075-中油锡山石油有限公司配餐项目",
        "222200150243-华东化工销售江苏物业项目",
        "SH3525Z043-大连石化江苏配餐项目",
        "SH3B25Z078-苏州销售太仓实训基地",
        "SH3B25Z077-江苏苏州销售分公司劳务输出",
        "SH3J25Z017-江苏南京销售分公司劳务输出",
        "SH3B25Z076-浙江杭州销售分公司劳务输出",
        "SH3B25Z079-江苏苏州销售分公司江乾站配餐项目",
        "222200150524-  江苏华东燃气运输分公司劳务输出0092（已停用）",
        "222200150516-  浙江杭州临安昆仑燃气配餐业务0031（已停用）",
        "222200150511-  浙江嘉兴销售分公司配餐业务0031（已停用）",
        "222200150512-浙江金华销售分公司配餐劳务输出项目",
        "222200150509-  浙江昆仑好客分公司配餐业务0031",
        "222200150518-浙江绍兴销售分公司其他餐饮业务",
        "222200150536-常州酒店",
        "222200150537-常州酒店",
        "222200150525-江苏无锡销售分公司劳务输出",
        "SH3625Z027-常州酒店项目部销售费用",
        "222200150218-南京商品代销项目",
        "222200150203-天然气销售浙江分公司配餐项目-代理",
        "222200150201-浙江湖州销售分公司配餐项目-代理",
        "222200150205-浙江绍兴销售分公司配餐项目-代理",
        "SHDX001-上海抵消",
        "HDDX003-华东分抵消",
        "HDDX001-华东分抵消",
        "HDDX004-华东分抵消",
        "HDDX005-华东分抵消",
        "HDDX002-华东分抵消",
        "SH3B26Z001-浙江湖州销售分公司配餐业务",
        "SH3B26Z004-浙江金华销售分公司配餐劳务输出项目",
        "222200150810-浙江绍兴销售分公司配餐劳务项目-黄山",
        "SH3B26Z002-中石化天然气分公司浙江销售配餐项目",
        "222200150809-黄山项目部能源转售项目",
        "222200150905-中国石油运输有限公司江苏分公司配餐项目",
        "SH3J26Z001-江苏镇江销售分公司劳务输出",
        "222200150910-南京酒店项目部公摊部门",
        "222200150911-黄鹂新村朝天宫会议室场地租赁项目",
        "LHCXL-蓝海新材料新市场拓展+提质增效",
        "222200150311-上海酒店物业费",
        "222200150301-  海洋石油局PA保洁项目0011",
        "222200150305-上海酒店租赁项目-未启用",
        "222200150216-上海中石油大厦项目",
        "222200150219-石油大厦资产项目",
        "222200150226-  常信拍卖保洁项目0013",
        "222200150211-中国移动上海分公司保洁项目",
        "222200150212-  江西安徽宁波车辆租赁项目0089",
        "SH3B26Z005-东北销售浙江宁波分公司配餐业务",
        "SH3B26Z006-东北销售浙江宁波分公司办公物业",
        "SH3526Z005-昆冈制造江苏配餐项目",
        "SH3526Z004-昆仑物流江苏配餐项目",
        "SH3526Z006-兰州石化江苏配餐项目（新）",
        "SH3526Z001-蓝海生产管理楼江苏配餐项目",
        "SH3526Z003-中油电能江苏配餐项目",
        "SH3526Z002-中油国际事业江苏物业项目",
        "XZCY0012-新市场拓展",
        "XZZY0012-自有产品销售"
      ]
    },
    "timestamp": "2026-05-09T17:53:15.283Z",
    "selectedIndicators": [
      "收入YTD",
      "2经营性采购支出",
      "3外购材料",
      "4食材耗用R",
      "5物料消耗R",
      "6油气管材",
      "7其他材料",
      "8外购燃料",
      "9外购动力",
      "10商旅采购成本",
      "11酒店佣金",
      "12运输费",
      "13经营性税费",
      "14油气分成支出",
      "15用工薪酬成本",
      "16外包劳务支出",
      "17维修费",
      "18租赁费",
      "19物业采暖费",
      "20绿化环境卫生费",
      "21五项费用",
      "22财产性税费",
      "23折旧折耗及摊销",
      "24其他固定成本",
      "25行政性罚款",
      "26信用减值损失",
      "27存货差额调整",
      "28财务费用",
      "29利息支出",
      "30资产处置损益",
      "31资产减值损失",
      "32营业外收支净额",
      "33投资收益",
      "34其他收益",
      "35其他非经常性损益",
      "36利润总额",
      "37所得税费用",
      "利润YTD"
    ]
  },
  {
    "id": "1778352357411",
    "userId": "1778345671048",
    "name": "iii",
    "filters": {
      "months": [],
      "ownerships": [
        "上海母公司",
        "常州酒店",
        "宜兴（华东分）",
        "南京酒店",
        "黄山酒店",
        "无锡酒店",
        "合并抵消",
        "华东分抵消"
      ],
      "managements": [
        "上海酒店项目部",
        "上海物业项目部",
        "南通蓝海项目部",
        "南京酒店项目部",
        "常州酒店项目部",
        "上海浦东华油本部",
        "无锡宜兴项目部",
        "黄山酒店项目部"
      ],
      "propertyTypes": [
        "物业业务",
        "餐饮业务",
        "其他业务",
        "酒店业务",
        "租赁业务",
        "管理业务"
      ],
      "projectNames": [
        "222200150308-中石化海洋局商城路基地物业服务项目",
        "222200150307-中石化海洋局商城路基地配餐项目",
        "222200150304-上海酒店能源转售项目",
        "222200150303-上海酒店",
        "222200150309-国家管网集团上海区域总部后勤配餐项目",
        "222200150241-中石油上海临港新材料研究院物业项目",
        "222200150239-蓝海新材料江苏物业项目",
        "222200150238-蓝海新材料江苏配餐项目",
        "222200150310-国家管网集团上海区域总部后勤物业服务项目",
        "222200150504-江苏销售分公司配餐业务",
        "222200150502-江苏常州酒店能源转售",
        "222200150501-常州酒店",
        "222200150236-江苏太仓燃气公司配餐项目-代理",
        "222200150214-上海酒店租赁项目",
        "222200150215-上海同盛大厦项目",
        "222200150505-江苏泰州销售配餐项目",
        "222200150231-世纪大道中石油上海大厦能源转售项目",
        "222200150230-上海世纪大道中石油综合餐饮项目",
        "222200150229-上海世纪大道中石油综合物业项目",
        "222200150228-川沙影院保洁项目",
        "222200150227-长泰影院保洁项目",
        "222200150225-寰球工程保洁项目",
        "222200150224-寰球工程安保项目",
        "222200150223-华东化工仓储安保项目",
        "222200150222-豪孚迪安保项目",
        "222200150217-华东分公司本部",
        "2222001501-宜兴度假村项目租赁项目（华东分）",
        "222200150506-江苏南通销售分公司配餐业务",
        "222200150508-浙江销售分公司配餐业务",
        "222200150915-蓝海新材料江苏配餐项目-代理",
        "222200150801-黄山阳光酒店分公司",
        "222200150914-天然气安徽分配餐项目",
        "222200150608-无锡销售配餐项目",
        "222200150607-天然气连云港销售分公司配餐项目",
        "222200150606-无锡润滑脂配餐项目",
        "222200150913-合肥昆仑燃气配餐项目",
        "222200150912-江苏苏州销售分公司江乾站配餐项目",
        "222200150808-黄山项目部销售项目",
        "222200150901-秣陵路99号综合楼酒店整租项目",
        "222200150902-黄鹂新村8栋酒店整租项目",
        "222200150903-黄鹂新村、金斯利、南湖住宅其他资产租赁项目",
        "222200150906-南京酒店能源转售项目",
        "222200150908-中国移动南京分公司基站",
        "222200150909-中国铁塔南京市分公司基站",
        "222200150603-无锡酒店商品销售项目",
        "222200150602-荣巷门面房租赁项目",
        "222200150601-马山檀溪1号温特莱酒店租赁项目",
        "222200150523-中油锡山石油有限公司配餐项目",
        "222200150522-江苏盐城销售分公司劳务输出",
        "222200150521-江苏苏州销售分公司劳务输出",
        "222200150520-江苏南京销售分公司劳务输出",
        "222200150519-江苏非油销售公司劳务输出",
        "222200150510-浙江湖州销售分公司配餐业务",
        "222200150507-江苏中石油国际事业有限公司配餐业务",
        "222200150527-东北销售浙江宁波分公司配餐业务",
        "222200150542-浙江湖州销售分公司配餐业务",
        "222200150541-浙江金华销售分公司配餐劳务输出项目",
        "222200150540-浙江绍兴销售分公司配餐劳务输出项目",
        "222200150539-江苏太仓燃气公司配餐项目",
        "222200150538-浙江杭州地质研究院配餐项目",
        "222200150535-中石化天然气分公司浙江销售配餐项目",
        "222200150534-浙江杭州地质研究院办公物业项目",
        "222200150533-江苏常州销售分公司配餐项目",
        "222200150532-江苏镇江销售分公司劳务输出",
        "222200150531-江苏南京中石油联安石化办公物业",
        "222200150530-东北销售浙江宁波分公司办公物业",
        "222200150528-东北销售浙江南京分公司配餐业务",
        "222200150526-浙江杭州销售分公司劳务输出",
        "222200150904-南京项目部项目销售",
        "222200150233-合肥昆仑燃气配餐项目-代理",
        "222200150234-天然气安徽分配餐项目-代理",
        "222200150237-无锡润滑脂配餐项目-代理",
        "222200150240-中石油上海临港新材料研究院配餐项目",
        "222200150242-陆家嘴金融城白领文化艺术中心物业项目",
        "222200150605-荣巷门面房能源转售项目",
        "222200150209-浙江销售分公司配餐项目-代理",
        "222200150235-浙江杭州地质研究院配餐项目-代理",
        "222200150232-浙江杭州地质研究院办公物业项目-代理",
        "222200150916-中石油昆仑合燃压缩气配餐项目",
        "222200150202-浙江昆仑好客分公司配餐项目-代理",
        "222200150918-东北销售南京分计量服务项目",
        "222200150917-东北销售宁波分计量项目",
        "222200150244-昆仑工程辽阳江苏物业项目",
        "222200150213-上海酒店租赁项目",
        "222200150609-江苏泰州销售配餐项目",
        "SH3J25Z016-江苏淮安销售分公司配餐劳务项目",
        "SH3B25Z075-中油锡山石油有限公司配餐项目",
        "222200150243-华东化工销售江苏物业项目",
        "SH3525Z043-大连石化江苏配餐项目",
        "SH3B25Z078-苏州销售太仓实训基地",
        "SH3B25Z077-江苏苏州销售分公司劳务输出",
        "SH3J25Z017-江苏南京销售分公司劳务输出",
        "SH3B25Z076-浙江杭州销售分公司劳务输出",
        "SH3B25Z079-江苏苏州销售分公司江乾站配餐项目",
        "222200150524-  江苏华东燃气运输分公司劳务输出0092（已停用）",
        "222200150516-  浙江杭州临安昆仑燃气配餐业务0031（已停用）",
        "222200150511-  浙江嘉兴销售分公司配餐业务0031（已停用）",
        "222200150512-浙江金华销售分公司配餐劳务输出项目",
        "222200150509-  浙江昆仑好客分公司配餐业务0031",
        "222200150518-浙江绍兴销售分公司其他餐饮业务",
        "222200150536-常州酒店",
        "222200150537-常州酒店",
        "222200150525-江苏无锡销售分公司劳务输出",
        "SH3625Z027-常州酒店项目部销售费用",
        "222200150218-南京商品代销项目",
        "222200150203-天然气销售浙江分公司配餐项目-代理",
        "222200150201-浙江湖州销售分公司配餐项目-代理",
        "222200150205-浙江绍兴销售分公司配餐项目-代理",
        "SHDX001-上海抵消",
        "HDDX003-华东分抵消",
        "HDDX001-华东分抵消",
        "HDDX004-华东分抵消",
        "HDDX005-华东分抵消",
        "HDDX002-华东分抵消",
        "SH3B26Z001-浙江湖州销售分公司配餐业务",
        "SH3B26Z004-浙江金华销售分公司配餐劳务输出项目",
        "222200150810-浙江绍兴销售分公司配餐劳务项目-黄山",
        "SH3B26Z002-中石化天然气分公司浙江销售配餐项目",
        "222200150809-黄山项目部能源转售项目",
        "222200150905-中国石油运输有限公司江苏分公司配餐项目",
        "SH3J26Z001-江苏镇江销售分公司劳务输出",
        "222200150910-南京酒店项目部公摊部门",
        "222200150911-黄鹂新村朝天宫会议室场地租赁项目",
        "LHCXL-蓝海新材料新市场拓展+提质增效",
        "222200150311-上海酒店物业费",
        "222200150301-  海洋石油局PA保洁项目0011",
        "222200150305-上海酒店租赁项目-未启用",
        "222200150216-上海中石油大厦项目",
        "222200150219-石油大厦资产项目",
        "222200150226-  常信拍卖保洁项目0013",
        "222200150211-中国移动上海分公司保洁项目",
        "222200150212-  江西安徽宁波车辆租赁项目0089",
        "SH3B26Z005-东北销售浙江宁波分公司配餐业务",
        "SH3B26Z006-东北销售浙江宁波分公司办公物业",
        "SH3526Z005-昆冈制造江苏配餐项目",
        "SH3526Z004-昆仑物流江苏配餐项目",
        "SH3526Z006-兰州石化江苏配餐项目（新）",
        "SH3526Z001-蓝海生产管理楼江苏配餐项目",
        "SH3526Z003-中油电能江苏配餐项目",
        "SH3526Z002-中油国际事业江苏物业项目",
        "XZCY0012-新市场拓展",
        "XZZY0012-自有产品销售"
      ]
    },
    "selectedIndicators": [
      "收入YTD",
      "2经营性采购支出",
      "3外购材料",
      "4食材耗用R",
      "5物料消耗R",
      "6油气管材",
      "7其他材料",
      "8外购燃料",
      "9外购动力",
      "10商旅采购成本",
      "11酒店佣金",
      "12运输费",
      "13经营性税费",
      "15用工薪酬成本",
      "16外包劳务支出",
      "17维修费",
      "18租赁费",
      "19物业采暖费",
      "21五项费用",
      "22财产性税费",
      "23折旧折耗及摊销",
      "24其他固定成本",
      "25行政性罚款",
      "26信用减值损失",
      "27存货差额调整",
      "28财务费用",
      "29利息支出",
      "30资产处置损益",
      "31资产减值损失",
      "32营业外收支净额",
      "33投资收益",
      "34其他收益",
      "35其他非经常性损益",
      "36利润总额",
      "37所得税费用",
      "利润YTD"
    ],
    "timestamp": "2026-05-09T20:11:10.471Z"
  }
]